tesseractfield/__init__.py
tesseractfield/fields.py
tesseractfield/tesseract.py
tesseractfield/urls.py
tesseractfield/views.py
tesseractfield/static/tesseractfield/css/tesseract.css
tesseractfield/static/tesseractfield/js/tesseract.js
tesseractfield/templates/tesseractfield/tesseract.html
djtesseract-0.0.6.dist-info/LICENSE
djtesseract-0.0.6.dist-info/METADATA
djtesseract-0.0.6.dist-info/WHEEL
djtesseract-0.0.6.dist-info/top_level.txt
djtesseract-0.0.6.dist-info/RECORD
