Metadata-Version: 2.1
Name: djtesseract
Version: 0.0.6
Summary: A small app providing a tesseract field for django 3.1.2
Home-page: https://github.com/YlmRdm/django-tesseractfield
Author: Yalim Erdem
Author-email: yalim.erdem@gmail.com
License: MIT License
Keywords: django,tesseract,field,admin
Platform: UNKNOWN
Classifier: Development Status :: 4 - Beta
Classifier: License :: OSI Approved :: MIT License
Classifier: Programming Language :: Python :: 3.9
Requires: django (>=3.0)
Requires-Dist: numpy (==1.19.2)
Requires-Dist: opencv-python (==4.4.0.44)
Requires-Dist: Pillow (==8.0.0)
Requires-Dist: pytesseract (==0.3.6)
